pytorch_imbalance_loss/__init__.py
pytorch_imbalance_loss/dice_loss.py
pytorch_imbalance_loss/focal_loss.py
pytorch_imbalance_loss/tversky_loss.py
pytorch_imbalance_loss-0.0.1.dist-info/LICENSE
pytorch_imbalance_loss-0.0.1.dist-info/WHEEL
pytorch_imbalance_loss-0.0.1.dist-info/METADATA
pytorch_imbalance_loss-0.0.1.dist-info/RECORD
