Metadata-Version: 2.1
Name: pytorch-imbalance-loss
Version: 0.0.1
Summary: Imbalance Losses in PyTorch for NLP
License: Apache License, Version 2.0
Author: Chenghao Mou
Author-email: mouchenghao@gmail.com
Requires-Python: >=3.8,<4.0
Classifier: License :: Other/Proprietary License
Classifier: Programming Language :: Python :: 3
Classifier: Programming Language :: Python :: 3.10
Classifier: Programming Language :: Python :: 3.8
Classifier: Programming Language :: Python :: 3.9
Requires-Dist: einops (>=0.3.2,<0.4.0)
Requires-Dist: numpy (>=1.22.3,<2.0.0)
Requires-Dist: torch (<=1.9.0)
Requires-Dist: torchtyping (>=0.1.4,<0.2.0)
Requires-Dist: typeguard (>=2.13.3,<3.0.0)
